{
    "top": [
        {
            "ruota": "Bari",
            "numeri": [
                41,
                67
            ],
            "score": 1580,
            "ultima_estrazione": [
                15,
                88,
                36,
                90,
                37
            ]
        },
        {
            "ruota": "Napoli",
            "numeri": [
                1,
                40
            ],
            "score": 1368,
            "ultima_estrazione": [
                83,
                72,
                60,
                16,
                21
            ]
        },
        {
            "ruota": "Palermo",
            "numeri": [
                45,
                90
            ],
            "score": 1248,
            "ultima_estrazione": [
                75,
                78,
                68,
                80,
                76
            ]
        }
    ],
    "jolly": {
        "ruota": "Bari",
        "numeri": [
            41,
            67
        ],
        "score": 1580,
        "ultima_estrazione": [
            15,
            88,
            36,
            90,
            37
        ]
    },
    "ambo_forte": [
        {
            "ruota": "Bari",
            "numeri": [
                41,
                67
            ],
            "score": 1580,
            "ultima_estrazione": [
                15,
                88,
                36,
                90,
                37
            ]
        },
        {
            "ruota": "Napoli",
            "numeri": [
                1,
                40
            ],
            "score": 1368,
            "ultima_estrazione": [
                83,
                72,
                60,
                16,
                21
            ]
        },
        {
            "ruota": "Palermo",
            "numeri": [
                45,
                90
            ],
            "score": 1248,
            "ultima_estrazione": [
                75,
                78,
                68,
                80,
                76
            ]
        },
        {
            "ruota": "Cagliari",
            "numeri": [
                41,
                63
            ],
            "score": 1192,
            "ultima_estrazione": [
                49,
                22,
                46,
                28,
                86
            ]
        },
        {
            "ruota": "Roma",
            "numeri": [
                7,
                17
            ],
            "score": 1144,
            "ultima_estrazione": [
                13,
                25,
                67,
                83,
                78
            ]
        },
        {
            "ruota": "Torino",
            "numeri": [
                49,
                88
            ],
            "score": 1136,
            "ultima_estrazione": [
                30,
                39,
                63,
                72,
                81
            ]
        },
        {
            "ruota": "Milano",
            "numeri": [
                61,
                77
            ],
            "score": 1080,
            "ultima_estrazione": [
                71,
                43,
                45,
                25,
                3
            ]
        },
        {
            "ruota": "Firenze",
            "numeri": [
                33,
                78
            ],
            "score": 1056,
            "ultima_estrazione": [
                7,
                85,
                14,
                84,
                55
            ]
        },
        {
            "ruota": "Venezia",
            "numeri": [
                17,
                79
            ],
            "score": 1012,
            "ultima_estrazione": [
                13,
                55,
                71,
                89,
                5
            ]
        },
        {
            "ruota": "Genova",
            "numeri": [
                6,
                49
            ],
            "score": 960,
            "ultima_estrazione": [
                89,
                69,
                88,
                41,
                81
            ]
        }
    ]
}