{
    "top": [
        {
            "ruota": "Roma",
            "numeri": [
                3,
                82
            ],
            "score": 139,
            "ultima_estrazione": [
                56,
                71,
                6,
                31,
                49
            ]
        },
        {
            "ruota": "Cagliari",
            "numeri": [
                4,
                90
            ],
            "score": 136,
            "ultima_estrazione": [
                20,
                58,
                64,
                90,
                31
            ]
        },
        {
            "ruota": "Torino",
            "numeri": [
                5,
                89
            ],
            "score": 134,
            "ultima_estrazione": [
                5,
                15,
                32,
                31,
                82
            ]
        },
        {
            "ruota": "Milano",
            "numeri": [
                8,
                90
            ],
            "score": 132,
            "ultima_estrazione": [
                46,
                44,
                71,
                59,
                85
            ]
        },
        {
            "ruota": "Genova",
            "numeri": [
                2,
                86
            ],
            "score": 124,
            "ultima_estrazione": [
                34,
                11,
                75,
                81,
                10
            ]
        },
        {
            "ruota": "Bari",
            "numeri": [
                9,
                81
            ],
            "score": 122,
            "ultima_estrazione": [
                42,
                44,
                87,
                52,
                39
            ]
        },
        {
            "ruota": "Firenze",
            "numeri": [
                6,
                82
            ],
            "score": 116,
            "ultima_estrazione": [
                37,
                23,
                45,
                36,
                62
            ]
        },
        {
            "ruota": "Venezia",
            "numeri": [
                15,
                87
            ],
            "score": 112,
            "ultima_estrazione": [
                1,
                32,
                27,
                12,
                50
            ]
        },
        {
            "ruota": "Palermo",
            "numeri": [
                14,
                85
            ],
            "score": 111,
            "ultima_estrazione": [
                85,
                60,
                81,
                28,
                9
            ]
        },
        {
            "ruota": "Napoli",
            "numeri": [
                16,
                90
            ],
            "score": 104,
            "ultima_estrazione": [
                69,
                24,
                75,
                86,
                20
            ]
        }
    ]
}